pytest_pyspec/__init__.py
pytest_pyspec/decorators.py
pytest_pyspec/plugin.py
pytest_pyspec/tree.py
pytest_pyspec-1.1.1.dist-info/METADATA
pytest_pyspec-1.1.1.dist-info/WHEEL
pytest_pyspec-1.1.1.dist-info/entry_points.txt
pytest_pyspec-1.1.1.dist-info/licenses/LICENSE
pytest_pyspec-1.1.1.dist-info/RECORD
