Metadata-Version: 2.4
Name: pytest-pyspec
Version: 1.1.1
Summary: The pytest-pyspec plugin transforms pytest output into a beautiful, readable format similar to RSpec. It provides semantic meaning to your tests by organizing them into descriptive hierarchies, using the prefixes `Describe`/`Test`, `With`/`Without`/`When`, and `test_`/`it_`, while allowing docstrings and decorators to override the descriptions.
Project-URL: Repository, https://github.com/felipecrp/pytest-pyspec
Project-URL: Issues, https://github.com/felipecrp/pytest-pyspec/issues
Author-email: Felipe Curty <felipecrp@gmail.com>
License-Expression: MIT
License-File: LICENSE
Classifier: Development Status :: 5 - Production/Stable
Classifier: Intended Audience :: Developers
Classifier: Operating System :: MacOS
Classifier: Operating System :: Microsoft :: Windows
Classifier: Operating System :: POSIX
Classifier: Operating System :: Unix
Classifier: Programming Language :: Python :: 3 :: Only
Classifier: Programming Language :: Python :: 3.10
Classifier: Programming Language :: Python :: 3.11
Classifier: Programming Language :: Python :: 3.12
Classifier: Programming Language :: Python :: 3.13
Classifier: Programming Language :: Python :: 3.14
Classifier: Topic :: Software Development :: Libraries
Classifier: Topic :: Software Development :: Testing
Classifier: Topic :: Utilities
Requires-Python: <4,>=3.10
Requires-Dist: pytest<10,>=9
